{"@context":"https://iiif.io/api/presentation/3/context.json","id":"https://markpbaggett.github.io/terminal-escape/api/facet/subject/dbeat.json","type":"Collection","label":{"none":["DBeat"]},"items":[{"id":"https://iiif.archive.org/iiif/Scum_Scum-demo-2014/manifest.json","type":"Manifest","label":{"none":["Scum - Scum demo 2014"]},"homepage":[{"id":"https://markpbaggett.github.io/terminal-escape/works/scum-scum-demo-2014","type":"Text","label":{"none":["Scum - Scum demo 2014"]}}]},{"id":"https://iiif.archive.org/iiif/Jvla_st-cassette-/manifest.json","type":"Manifest","label":{"none":["Jävla - s/t cassette "]},"homepage":[{"id":"https://markpbaggett.github.io/terminal-escape/works/javla-st-cassette","type":"Text","label":{"none":["Jävla - s/t cassette "]}}]},{"id":"https://iiif.archive.org/iiif/VORGR/manifest.json","type":"Manifest","label":{"none":["VORGÄR"]},"homepage":[{"id":"https://markpbaggett.github.io/terminal-escape/works/vorgar","type":"Text","label":{"none":["VORGÄR"]}}]}],"partOf":[{"id":"https://markpbaggett.github.io/terminal-escape/api/facet/subject.json","type":"Collection"}],"summary":{"none":["subject"]},"homepage":[{"id":"https://markpbaggett.github.io/terminal-escape/search?subject=dbeat","type":"Text","label":{"none":["DBeat"]}}]}