{"@context":"https://iiif.io/api/presentation/3/context.json","id":"https://markpbaggett.github.io/terminal-escape/api/facet/subject/russia.json","type":"Collection","label":{"none":["russia"]},"items":[{"id":"https://iiif.archive.org/iiif/Jinx_Jinx/manifest.json","type":"Manifest","label":{"none":["Jinx - Jinx"]},"homepage":[{"id":"https://markpbaggett.github.io/terminal-escape/works/jinx-jinx","type":"Text","label":{"none":["Jinx - Jinx"]}}]},{"id":"https://iiif.archive.org/iiif/Sozna--YoungTribe_Ephemeral/manifest.json","type":"Manifest","label":{"none":["Sozna & YoungTribe - Ephemeral"]},"homepage":[{"id":"https://markpbaggett.github.io/terminal-escape/works/sozna-and-youngtribe-ephemeral","type":"Text","label":{"none":["Sozna & YoungTribe - Ephemeral"]}}]},{"id":"https://iiif.archive.org/iiif/Grave-Disgrace_Grave-Disgrace-st-cassette/manifest.json","type":"Manifest","label":{"none":["Grave Disgrace - Grave Disgrace s/t cassette"]},"homepage":[{"id":"https://markpbaggett.github.io/terminal-escape/works/grave-disgrace-grave-disgrace-st-cassette","type":"Text","label":{"none":["Grave Disgrace - Grave Disgrace s/t cassette"]}}]},{"id":"https://iiif.archive.org/iiif/TerrrStriker_Hordes-Of-Armageddon/manifest.json","type":"Manifest","label":{"none":["TerrörStriker - Hordes Of Armageddon"]},"homepage":[{"id":"https://markpbaggett.github.io/terminal-escape/works/terrorstriker-hordes-of-armageddon","type":"Text","label":{"none":["TerrörStriker - Hordes Of Armageddon"]}}]},{"id":"https://iiif.archive.org/iiif/Aura-Level-Fountain_Tulan-Tulan-Axcanpa/manifest.json","type":"Manifest","label":{"none":["Aura Level Fountain - Tulan Tulan Axcanpa"]},"homepage":[{"id":"https://markpbaggett.github.io/terminal-escape/works/aura-level-fountain-tulan-tulan-axcanpa","type":"Text","label":{"none":["Aura Level Fountain - Tulan Tulan Axcanpa"]}}]},{"id":"https://iiif.archive.org/iiif/va---We-Are-All-Positive_va---We-All-Are-Positive-compilation/manifest.json","type":"Manifest","label":{"none":["v/a - We Are All Positive - v/a - We All Are Positive compilation"]},"homepage":[{"id":"https://markpbaggett.github.io/terminal-escape/works/va-we-are-all-positive-va-we-all-are-positive-compilation","type":"Text","label":{"none":["v/a - We Are All Positive - v/a - We All Are Positive compilation"]}}]},{"id":"https://iiif.archive.org/iiif/Black-River_Tape/manifest.json","type":"Manifest","label":{"none":["Черная Речка (Black River) - Сторона А"]},"homepage":[{"id":"https://markpbaggett.github.io/terminal-escape/works/chernaya-rechka-black-river-storona-a","type":"Text","label":{"none":["Черная Речка (Black River) - Сторона А"]}}]},{"id":"https://iiif.archive.org/iiif/The-Ratcatcher_st-cassette/manifest.json","type":"Manifest","label":{"none":["The Ratcatcher - s/t cassette"]},"homepage":[{"id":"https://markpbaggett.github.io/terminal-escape/works/the-ratcatcher-st-cassette","type":"Text","label":{"none":["The Ratcatcher - s/t cassette"]}}]},{"id":"https://iiif.archive.org/iiif/UCHITEL-TRUDA/manifest.json","type":"Manifest","label":{"none":["Учитель Труда (Uchitel Truda) - Ne V Obidu"]},"homepage":[{"id":"https://markpbaggett.github.io/terminal-escape/works/uchitel-truda-uchitel-truda-ne-v-obidu","type":"Text","label":{"none":["Учитель Труда (Uchitel Truda) - Ne V Obidu"]}}]},{"id":"https://iiif.archive.org/iiif/MORBITAL_War-Horror-demo/manifest.json","type":"Manifest","label":{"none":["MORBITAL - War Horror demo"]},"homepage":[{"id":"https://markpbaggett.github.io/terminal-escape/works/morbital-war-horror-demo","type":"Text","label":{"none":["MORBITAL - War Horror demo"]}}]},{"id":"https://iiif.archive.org/iiif/Special-Conditions_Tape/manifest.json","type":"Manifest","label":{"none":["Особые Условия (SPECIAL CONDITIONS) - Страх уйти без сожаления"]},"homepage":[{"id":"https://markpbaggett.github.io/terminal-escape/works/osobye-usloviya-special-conditions-strah-ujti-bez-sozhaleniya","type":"Text","label":{"none":["Особые Условия (SPECIAL CONDITIONS) - Страх уйти без сожаления"]}}]},{"id":"https://iiif.archive.org/iiif/Unbroken-Bones_Batallion-Of-Bones-demo-2012/manifest.json","type":"Manifest","label":{"none":["Unbroken Bones - Batallion Of Bones demo 2012"]},"homepage":[{"id":"https://markpbaggett.github.io/terminal-escape/works/unbroken-bones-batallion-of-bones-demo-2012","type":"Text","label":{"none":["Unbroken Bones - Batallion Of Bones demo 2012"]}}]},{"id":"https://iiif.archive.org/iiif/Yurodiviye_Yurodiviye-cassette-2015/manifest.json","type":"Manifest","label":{"none":["Yurodiviye - Yurodiviye cassette 2015"]},"homepage":[{"id":"https://markpbaggett.github.io/terminal-escape/works/yurodiviye-yurodiviye-cassette-2015","type":"Text","label":{"none":["Yurodiviye - Yurodiviye cassette 2015"]}}]},{"id":"https://iiif.archive.org/iiif/July-Days_Dark-Thoughts/manifest.json","type":"Manifest","label":{"none":["Июльские дни (July Days) - Июльские дни (Dark Thoughts) demo 2014"]},"homepage":[{"id":"https://markpbaggett.github.io/terminal-escape/works/iyulskie-dni-july-days-iyulskie-dni-dark-thoughts-demo-2014","type":"Text","label":{"none":["Июльские дни (July Days) - Июльские дни (Dark Thoughts) demo 2014"]}}]},{"id":"https://iiif.archive.org/iiif/Afterlife_Afterlife-cassette-2015/manifest.json","type":"Manifest","label":{"none":["Afterlife - Afterlife cassette 2015"]},"homepage":[{"id":"https://markpbaggett.github.io/terminal-escape/works/afterlife-afterlife-cassette-2015","type":"Text","label":{"none":["Afterlife - Afterlife cassette 2015"]}}]},{"id":"https://iiif.archive.org/iiif/unknown-artist_unknown-Russian-hip-hop/manifest.json","type":"Manifest","label":{"none":["unknown artist - unknown (Russian hip hop)"]},"homepage":[{"id":"https://markpbaggett.github.io/terminal-escape/works/unknown-artist-unknown-russian-hip-hop","type":"Text","label":{"none":["unknown artist - unknown (Russian hip hop)"]}}]}],"partOf":[{"id":"https://markpbaggett.github.io/terminal-escape/api/facet/subject.json","type":"Collection"}],"summary":{"none":["subject"]},"homepage":[{"id":"https://markpbaggett.github.io/terminal-escape/search?subject=russia","type":"Text","label":{"none":["russia"]}}]}