{"@context":"https://iiif.io/api/presentation/3/context.json","id":"https://markpbaggett.github.io/terminal-escape/api/facet/subject/uk82.json","type":"Collection","label":{"none":["UK82"]},"items":[{"id":"https://iiif.archive.org/iiif/UK-PUNK/manifest.json","type":"Manifest","label":{"none":["UK PUNK"]},"homepage":[{"id":"https://markpbaggett.github.io/terminal-escape/works/uk-punk","type":"Text","label":{"none":["UK PUNK"]}}]}],"partOf":[{"id":"https://markpbaggett.github.io/terminal-escape/api/facet/subject.json","type":"Collection"}],"summary":{"none":["subject"]},"homepage":[{"id":"https://markpbaggett.github.io/terminal-escape/search?subject=uk82","type":"Text","label":{"none":["UK82"]}}]}