{"@context":"https://iiif.io/api/presentation/3/context.json","id":"https://markpbaggett.github.io/terminal-escape/api/facet/artist/crazy-doberman.json","type":"Collection","label":{"none":["Crazy Doberman"]},"items":[{"id":"https://iiif.archive.org/iiif/Crazy-Doberman_Spin-Age-Blasters/manifest.json","type":"Manifest","label":{"none":["Crazy Doberman - Spin Age Blasters"]},"homepage":[{"id":"https://markpbaggett.github.io/terminal-escape/works/crazy-doberman-spin-age-blasters","type":"Text","label":{"none":["Crazy Doberman - Spin Age Blasters"]}}]}],"partOf":[{"id":"https://markpbaggett.github.io/terminal-escape/api/facet/artist.json","type":"Collection"}],"summary":{"none":["artist"]},"homepage":[{"id":"https://markpbaggett.github.io/terminal-escape/search?artist=crazy-doberman","type":"Text","label":{"none":["Crazy Doberman"]}}]}