{"@context":"https://iiif.io/api/presentation/3/context.json","id":"https://markpbaggett.github.io/terminal-escape/api/facet/artist/hope-followed-by-despair.json","type":"Collection","label":{"none":["Hope Followed By Despair"]},"items":[{"id":"https://iiif.archive.org/iiif/Hope-Followed-By-Despair_Hope-Followed-By-Despair-cassette/manifest.json","type":"Manifest","label":{"none":["Hope Followed By Despair - Hope Followed By Despair cassette"]},"homepage":[{"id":"https://markpbaggett.github.io/terminal-escape/works/hope-followed-by-despair-hope-followed-by-despair-cassette","type":"Text","label":{"none":["Hope Followed By Despair - Hope Followed By Despair cassette"]}}]}],"partOf":[{"id":"https://markpbaggett.github.io/terminal-escape/api/facet/artist.json","type":"Collection"}],"summary":{"none":["artist"]},"homepage":[{"id":"https://markpbaggett.github.io/terminal-escape/search?artist=hope-followed-by-despair","type":"Text","label":{"none":["Hope Followed By Despair"]}}]}