{"@context":"https://iiif.io/api/presentation/3/context.json","id":"https://markpbaggett.github.io/terminal-escape/api/facet/artist/institute.json","type":"Collection","label":{"none":["Institute"]},"items":[{"id":"https://iiif.archive.org/iiif/Institute_Institute-demo/manifest.json","type":"Manifest","label":{"none":["Institute - Institute demo"]},"homepage":[{"id":"https://markpbaggett.github.io/terminal-escape/works/institute-institute-demo","type":"Text","label":{"none":["Institute - Institute demo"]}}]}],"partOf":[{"id":"https://markpbaggett.github.io/terminal-escape/api/facet/artist.json","type":"Collection"}],"summary":{"none":["artist"]},"homepage":[{"id":"https://markpbaggett.github.io/terminal-escape/search?artist=institute","type":"Text","label":{"none":["Institute"]}}]}