{"@context":"https://iiif.io/api/presentation/3/context.json","id":"https://markpbaggett.github.io/terminal-escape/api/facet/artist/kgb.json","type":"Collection","label":{"none":["K.G.B."]},"items":[{"id":"https://iiif.archive.org/iiif/K.G.B._K.G.B.-demo-1996/manifest.json","type":"Manifest","label":{"none":["K.G.B. - K.G.B. demo 1996"]},"homepage":[{"id":"https://markpbaggett.github.io/terminal-escape/works/kgb-kgb-demo-1996","type":"Text","label":{"none":["K.G.B. - K.G.B. demo 1996"]}}]}],"partOf":[{"id":"https://markpbaggett.github.io/terminal-escape/api/facet/artist.json","type":"Collection"}],"summary":{"none":["artist"]},"homepage":[{"id":"https://markpbaggett.github.io/terminal-escape/search?artist=kgb","type":"Text","label":{"none":["K.G.B."]}}]}