{"@context":"https://iiif.io/api/presentation/3/context.json","id":"https://markpbaggett.github.io/terminal-escape/api/facet/artist/machine-gun-etiquette.json","type":"Collection","label":{"none":["Machine Gun Etiquette"]},"items":[{"id":"https://iiif.archive.org/iiif/Machine-Gun-Etiquette_No-Frills/manifest.json","type":"Manifest","label":{"none":["Machine Gun Etiquette - No Frills"]},"homepage":[{"id":"https://markpbaggett.github.io/terminal-escape/works/machine-gun-etiquette-no-frills","type":"Text","label":{"none":["Machine Gun Etiquette - No Frills"]}}]}],"partOf":[{"id":"https://markpbaggett.github.io/terminal-escape/api/facet/artist.json","type":"Collection"}],"summary":{"none":["artist"]},"homepage":[{"id":"https://markpbaggett.github.io/terminal-escape/search?artist=machine-gun-etiquette","type":"Text","label":{"none":["Machine Gun Etiquette"]}}]}