{"@context":"https://iiif.io/api/presentation/3/context.json","id":"https://markpbaggett.github.io/terminal-escape/api/facet/artist/meat-dreams.json","type":"Collection","label":{"none":["Meat Dreams"]},"items":[{"id":"https://iiif.archive.org/iiif/Meat-Dreams_Its-Out-Tour-Tape-2017/manifest.json","type":"Manifest","label":{"none":["Meat Dreams - Its Out: Tour Tape 2017"]},"homepage":[{"id":"https://markpbaggett.github.io/terminal-escape/works/meat-dreams-its-out-tour-tape-2017","type":"Text","label":{"none":["Meat Dreams - Its Out: Tour Tape 2017"]}}]}],"partOf":[{"id":"https://markpbaggett.github.io/terminal-escape/api/facet/artist.json","type":"Collection"}],"summary":{"none":["artist"]},"homepage":[{"id":"https://markpbaggett.github.io/terminal-escape/search?artist=meat-dreams","type":"Text","label":{"none":["Meat Dreams"]}}]}