{"@context":"https://iiif.io/api/presentation/3/context.json","id":"https://markpbaggett.github.io/terminal-escape/api/facet/artist/perfect-pussy.json","type":"Collection","label":{"none":["Perfect Pussy"]},"items":[{"id":"https://iiif.archive.org/iiif/Perfect-Pussy_I-Have-Lost-All-Desire-For-Feeling/manifest.json","type":"Manifest","label":{"none":["Perfect Pussy - I Have Lost All Desire For Feeling"]},"homepage":[{"id":"https://markpbaggett.github.io/terminal-escape/works/perfect-pussy-i-have-lost-all-desire-for-feeling","type":"Text","label":{"none":["Perfect Pussy - I Have Lost All Desire For Feeling"]}}]}],"partOf":[{"id":"https://markpbaggett.github.io/terminal-escape/api/facet/artist.json","type":"Collection"}],"summary":{"none":["artist"]},"homepage":[{"id":"https://markpbaggett.github.io/terminal-escape/search?artist=perfect-pussy","type":"Text","label":{"none":["Perfect Pussy"]}}]}