{"@context":"https://iiif.io/api/presentation/3/context.json","id":"https://markpbaggett.github.io/terminal-escape/api/facet/artist/retardo-montalban.json","type":"Collection","label":{"none":["Retardo Montalban"]},"items":[{"id":"https://iiif.archive.org/iiif/Retardo-Montalban_Bite-The-Pork/manifest.json","type":"Manifest","label":{"none":["Retardo Montalban - Bite The Pork"]},"homepage":[{"id":"https://markpbaggett.github.io/terminal-escape/works/retardo-montalban-bite-the-pork","type":"Text","label":{"none":["Retardo Montalban - Bite The Pork"]}}]}],"partOf":[{"id":"https://markpbaggett.github.io/terminal-escape/api/facet/artist.json","type":"Collection"}],"summary":{"none":["artist"]},"homepage":[{"id":"https://markpbaggett.github.io/terminal-escape/search?artist=retardo-montalban","type":"Text","label":{"none":["Retardo Montalban"]}}]}