{"@context":"https://iiif.io/api/presentation/3/context.json","id":"https://markpbaggett.github.io/terminal-escape/api/facet/artist/skullcaster.json","type":"Collection","label":{"none":["Skullcaster"]},"items":[{"id":"https://iiif.archive.org/iiif/Skullcaster_Revaluation/manifest.json","type":"Manifest","label":{"none":["Skullcaster - Revaluation"]},"homepage":[{"id":"https://markpbaggett.github.io/terminal-escape/works/skullcaster-revaluation","type":"Text","label":{"none":["Skullcaster - Revaluation"]}}]}],"partOf":[{"id":"https://markpbaggett.github.io/terminal-escape/api/facet/artist.json","type":"Collection"}],"summary":{"none":["artist"]},"homepage":[{"id":"https://markpbaggett.github.io/terminal-escape/search?artist=skullcaster","type":"Text","label":{"none":["Skullcaster"]}}]}