{"@context":"https://iiif.io/api/presentation/3/context.json","id":"https://markpbaggett.github.io/terminal-escape/api/facet/artist/sun-ra.json","type":"Collection","label":{"none":["Sun Ra"]},"items":[{"id":"https://iiif.archive.org/iiif/Sun-Ra_Nuclear-War--Ra-To-The-Rescue/manifest.json","type":"Manifest","label":{"none":["Sun Ra - Nuclear War + Ra To The Rescue"]},"homepage":[{"id":"https://markpbaggett.github.io/terminal-escape/works/sun-ra-nuclear-war-ra-to-the-rescue","type":"Text","label":{"none":["Sun Ra - Nuclear War + Ra To The Rescue"]}}]}],"partOf":[{"id":"https://markpbaggett.github.io/terminal-escape/api/facet/artist.json","type":"Collection"}],"summary":{"none":["artist"]},"homepage":[{"id":"https://markpbaggett.github.io/terminal-escape/search?artist=sun-ra","type":"Text","label":{"none":["Sun Ra"]}}]}