{"@context":"https://iiif.io/api/presentation/3/context.json","id":"https://markpbaggett.github.io/terminal-escape/api/facet/artist/unarm.json","type":"Collection","label":{"none":["UNARM"]},"items":[{"id":"https://iiif.archive.org/iiif/UNARM_The-Mob-Of-Survivors-West-Coast-Tour-Tape-2017/manifest.json","type":"Manifest","label":{"none":["UNARM - The Mob Of Survivors: West Coast Tour Tape 2017"]},"homepage":[{"id":"https://markpbaggett.github.io/terminal-escape/works/unarm-the-mob-of-survivors-west-coast-tour-tape-2017","type":"Text","label":{"none":["UNARM - The Mob Of Survivors: West Coast Tour Tape 2017"]}}]}],"partOf":[{"id":"https://markpbaggett.github.io/terminal-escape/api/facet/artist.json","type":"Collection"}],"summary":{"none":["artist"]},"homepage":[{"id":"https://markpbaggett.github.io/terminal-escape/search?artist=unarm","type":"Text","label":{"none":["UNARM"]}}]}