{"@context":"https://iiif.io/api/presentation/3/context.json","id":"https://markpbaggett.github.io/terminal-escape/api/facet/artist/va-disturbing-the-common-peace.json","type":"Collection","label":{"none":["v/a - Disturbing The Common Peace"]},"items":[{"id":"https://iiif.archive.org/iiif/va---Disturbing-The-Common-Peace_---/manifest.json","type":"Manifest","label":{"none":["v/a - Disturbing The Common Peace - ΔΙΑΤΆΡΑΞΗ ΚΟΙΝΉΣ ΗΣΥΧΊΑΣ "]},"homepage":[{"id":"https://markpbaggett.github.io/terminal-escape/works/va-disturbing-the-common-peace-diatara3h-koinhs-hsyxias","type":"Text","label":{"none":["v/a - Disturbing The Common Peace - ΔΙΑΤΆΡΑΞΗ ΚΟΙΝΉΣ ΗΣΥΧΊΑΣ "]}}]}],"partOf":[{"id":"https://markpbaggett.github.io/terminal-escape/api/facet/artist.json","type":"Collection"}],"summary":{"none":["artist"]},"homepage":[{"id":"https://markpbaggett.github.io/terminal-escape/search?artist=va-disturbing-the-common-peace","type":"Text","label":{"none":["v/a - Disturbing The Common Peace"]}}]}