{"@context":"https://iiif.io/api/presentation/3/context.json","id":"https://markpbaggett.github.io/terminal-escape/api/facet/artist/va-nema-vopia-nedeljom-uvece.json","type":"Collection","label":{"none":["v/a - Nema Vopia Nedeljom Uvece"]},"items":[{"id":"https://iiif.archive.org/iiif/va---Nema-Vopia-Nedeljom-Uvece_va---Nema-Vopia-Nedeljom-Uvece/manifest.json","type":"Manifest","label":{"none":["v/a - Nema Vopia Nedeljom Uvece - v/a - Nema Vopia Nedeljom Uvece"]},"homepage":[{"id":"https://markpbaggett.github.io/terminal-escape/works/va-nema-vopia-nedeljom-uvece-va-nema-vopia-nedeljom-uvece","type":"Text","label":{"none":["v/a - Nema Vopia Nedeljom Uvece - v/a - Nema Vopia Nedeljom Uvece"]}}]}],"partOf":[{"id":"https://markpbaggett.github.io/terminal-escape/api/facet/artist.json","type":"Collection"}],"summary":{"none":["artist"]},"homepage":[{"id":"https://markpbaggett.github.io/terminal-escape/search?artist=va-nema-vopia-nedeljom-uvece","type":"Text","label":{"none":["v/a - Nema Vopia Nedeljom Uvece"]}}]}