{"@context":"https://iiif.io/api/presentation/3/context.json","id":"https://markpbaggett.github.io/terminal-escape/api/facet/artist/weird-unknown-guy.json","type":"Collection","label":{"none":["weird unknown guy"]},"items":[{"id":"https://iiif.archive.org/iiif/weird-unknown-guy_weird-unknown-cassette/manifest.json","type":"Manifest","label":{"none":["weird unknown guy - weird unknown cassette"]},"homepage":[{"id":"https://markpbaggett.github.io/terminal-escape/works/weird-unknown-guy-weird-unknown-cassette","type":"Text","label":{"none":["weird unknown guy - weird unknown cassette"]}}]}],"partOf":[{"id":"https://markpbaggett.github.io/terminal-escape/api/facet/artist.json","type":"Collection"}],"summary":{"none":["artist"]},"homepage":[{"id":"https://markpbaggett.github.io/terminal-escape/search?artist=weird-unknown-guy","type":"Text","label":{"none":["weird unknown guy"]}}]}